AUTHORS.rst
CONTRIBUTING.rst
HISTORY.rst
LICENSE
MANIFEST.in
README.rst
setup.cfg
setup.py
docs/Makefile
docs/authors.rst
docs/conf.py
docs/contributing.rst
docs/history.rst
docs/index.rst
docs/installation.rst
docs/make.bat
docs/readme.rst
docs/usage.rst
flir_ptu/__init__.py
flir_ptu/ptu.py
flir_ptu/stream.py
flir_ptu.egg-info/PKG-INFO
flir_ptu.egg-info/SOURCES.txt
flir_ptu.egg-info/dependency_links.txt
flir_ptu.egg-info/not-zip-safe
flir_ptu.egg-info/top_level.txt
tests/test_flir.py